ups_rating/__init__.py
ups_rating/sdk.py
ups_rating/hooks/__init__.py
ups_rating/hooks/hook.py
ups_rating/models/__init__.py
ups_rating/models/adjusted_height_unit_of_measurement.py
ups_rating/models/alert_detail_element_level_information.py
ups_rating/models/alternate_delivery_address_address.py
ups_rating/models/base.py
ups_rating/models/bill_receiver_address.py
ups_rating/models/bill_third_party_address.py
ups_rating/models/billing_weight_unit_of_measurement.py
ups_rating/models/cod_cod_amount.py
ups_rating/models/commodity_nmfc.py
ups_rating/models/delivery_time_information_pickup.py
ups_rating/models/delivery_time_information_return_contract_services.py
ups_rating/models/dim_weight_unit_of_measurement.py
ups_rating/models/dimensions_unit_of_measurement.py
ups_rating/models/dry_ice_dry_ice_weight.py
ups_rating/models/dry_ice_weight_unit_of_measurement.py
ups_rating/models/element_level_information_element_identifier.py
ups_rating/models/estimated_arrival_arrival.py
ups_rating/models/estimated_arrival_pickup.py
ups_rating/models/freight_density_info_adjusted_height.py
ups_rating/models/freight_density_info_handling_units.py
ups_rating/models/freight_shipment_information_freight_density_info.py
ups_rating/models/frs_payment_information_address.py
ups_rating/models/frs_payment_information_type.py
ups_rating/models/frs_shipment_data_freight_density_rate.py
ups_rating/models/frs_shipment_data_handling_units.py
ups_rating/models/frs_shipment_data_transportation_charges.py
ups_rating/models/handling_units_adjusted_height.py
ups_rating/models/handling_units_dimensions.py
ups_rating/models/handling_units_type.py
ups_rating/models/handling_units_unit_of_measurement.py
ups_rating/models/haz_mat_haz_mat_chemical_record.py
ups_rating/models/insurance_basic_flexible_parcel_indicator.py
ups_rating/models/insurance_extended_flexible_parcel_indicator.py
ups_rating/models/insurance_time_in_transit_flexible_parcel_indicator.py
ups_rating-1.0.0.dist-info/LICENSE
ups_rating-1.0.0.dist-info/METADATA
ups_rating-1.0.0.dist-info/WHEEL
ups_rating-1.0.0.dist-info/top_level.txt
ups_rating-1.0.0.dist-info/RECORD
