Metadata-Version: 2.1
Name: ups-rating
Version: 1.0.0
Summary: Compare delivery services and shipping rates to determine the best option.
License: MIT
Requires-Python: >=3.7
License-File: LICENSE
Requires-Dist: requests >=2.31.0
